sample_factory/__init__.py
sample_factory/enjoy.py
sample_factory/train.py
sample_factory/algo/__init__.py
sample_factory/algo/evaluators/__init__.py
sample_factory/algo/evaluators/default_evaluator.py
sample_factory/algo/learning/__init__.py
sample_factory/algo/learning/batcher.py
sample_factory/algo/learning/learner.py
sample_factory/algo/learning/learner_worker.py
sample_factory/algo/learning/rnn_utils.py
sample_factory/algo/runners/__init__.py
sample_factory/algo/runners/runner.py
sample_factory/algo/runners/runner_parallel.py
sample_factory/algo/runners/runner_serial.py
sample_factory/algo/sampling/__init__.py
sample_factory/algo/sampling/batched_sampling.py
sample_factory/algo/sampling/inference_worker.py
sample_factory/algo/sampling/non_batched_sampling.py
sample_factory/algo/sampling/rollout_worker.py
sample_factory/algo/sampling/sampler.py
sample_factory/algo/sampling/sampling_utils.py
sample_factory/algo/sampling/simplified_sampling_api.py
sample_factory/algo/utils/__init__.py
sample_factory/algo/utils/action_distributions.py
sample_factory/algo/utils/agent_policy_mapping.py
sample_factory/algo/utils/context.py
sample_factory/algo/utils/env_info.py
sample_factory/algo/utils/gymnasium_utils.py
sample_factory/algo/utils/heartbeat.py
sample_factory/algo/utils/make_env.py
sample_factory/algo/utils/misc.py
sample_factory/algo/utils/model_sharing.py
sample_factory/algo/utils/multiprocessing_utils.py
sample_factory/algo/utils/optimizers.py
sample_factory/algo/utils/rl_utils.py
sample_factory/algo/utils/running_mean_std.py
sample_factory/algo/utils/shared_buffers.py
sample_factory/algo/utils/tensor_dict.py
sample_factory/algo/utils/tensor_utils.py
sample_factory/algo/utils/torch_utils.py
sample_factory/algo/utils/spaces/__init__.py
sample_factory/algo/utils/spaces/discretized.py
sample_factory/cfg/__init__.py
sample_factory/cfg/arguments.py
sample_factory/cfg/cfg.py
sample_factory/cfg/configurable.py
sample_factory/envs/__init__.py
sample_factory-2.1.1.dist-info/LICENSE
sample_factory-2.1.1.dist-info/METADATA
sample_factory-2.1.1.dist-info/WHEEL
sample_factory-2.1.1.dist-info/top_level.txt
sample_factory-2.1.1.dist-info/RECORD
