Metadata-Version: 2.1
Name: sample-factory
Version: 2.1.1
Summary: High throughput asynchronous reinforcement learning framework
Home-page: https://github.com/alex-petrenko/sample-factory
Author: Aleksei Petrenko
License: MIT
Project-URL: Github, https://github.com/alex-petrenko/sample-factory
Project-URL: Videos, https://sites.google.com/view/sample-factory
Keywords: asynchronous reinforcement learning policy gradient ppo appo impala ai
Requires-Python: >=3.8
License-File: LICENSE
Requires-Dist: numpy (<2.0,>=1.18.1)
Requires-Dist: torch (!=1.13.0,<3.0,>=1.9)
Requires-Dist: gymnasium (<1.0,>=0.27)
Requires-Dist: pyglet
Requires-Dist: tensorboard (>=1.15.0)
Requires-Dist: tensorboardx (>=2.0)
Requires-Dist: psutil (>=5.7.0)
Requires-Dist: threadpoolctl (>=2.0.0)
Requires-Dist: colorlog
Requires-Dist: signal-slot-mp (<2.0,>=1.0.3)
Requires-Dist: filelock
Requires-Dist: opencv-python
Requires-Dist: wandb (>=0.12.9)
Requires-Dist: huggingface-hub (<1.0,>=0.10.0)
Provides-Extra: atari
Requires-Dist: gymnasium[accept-rom-license,atari] ; extra == 'atari'
Provides-Extra: dev
Requires-Dist: black ; extra == 'dev'
Requires-Dist: isort (>=5.12) ; extra == 'dev'
Requires-Dist: pytest (<8.0) ; extra == 'dev'
Requires-Dist: flake8 ; extra == 'dev'
Requires-Dist: pre-commit ; extra == 'dev'
Requires-Dist: twine ; extra == 'dev'
Requires-Dist: mkdocs-material ; extra == 'dev'
Requires-Dist: mkdocs-minify-plugin ; extra == 'dev'
Requires-Dist: mkdocs-redirects ; extra == 'dev'
Requires-Dist: mkdocs-git-revision-date-localized-plugin ; extra == 'dev'
Requires-Dist: mkdocs-git-committers-plugin-2 ; extra == 'dev'
Requires-Dist: mkdocs-git-authors-plugin ; extra == 'dev'
Requires-Dist: gymnasium[accept-rom-license,atari] ; extra == 'dev'
Requires-Dist: gymnasium[mujoco] ; extra == 'dev'
Requires-Dist: mujoco (<=2.3.3) ; extra == 'dev'
Provides-Extra: envpool
Requires-Dist: envpool ; extra == 'envpool'
Provides-Extra: mujoco
Requires-Dist: gymnasium[mujoco] ; extra == 'mujoco'
Requires-Dist: mujoco (<=2.3.3) ; extra == 'mujoco'
Provides-Extra: vizdoom
Requires-Dist: vizdoom (<2.0) ; extra == 'vizdoom'
Requires-Dist: gymnasium[classic_control] ; extra == 'vizdoom'
